Workbook

Sheet Assunzioni
A1: VirtualBNB — Assunzioni del Modello
A2: Celle in BLU = da modificare con i tuoi numeri reali. Celle GIALLE = assunzioni-chiave da verificare per prime.
A4: Commissioni per tier
A5: Tier | B5: Valore | D5: Fonte
A6: Essenziale (% sul revenue netto) | B6: 0.25 | D6: Prezzi.jsx — certo
A7: Smart (% sul revenue netto) | B7: 0.28 | D7: Prezzi.jsx — certo
A8: Premium (fisso €/mese) | B8: 650 | D8: Prezzi.jsx — certo
A10: Setup una tantum
A11: Essenziale | B11: 350
A12: Smart | B12: 450
A13: Premium | B13: 0
A15: Break-even Smart → Premium (revenue mensile a cui i due modelli si equivalgono) | B15: =B8/B7 -> 2321.4286
A17: Costi variabili stimati per immobile (mensili)
A18: Voce | B18: Valore | D18: Nota
A19: AI WhatsApp / Anthropic API | B19: 2 | D19: Calcolato in sessione precedente — costo reale basso e stabile
A20: PriceLabs / Wheelhouse (quota per immobile) | B20: 22 | D20: STIMA — verifica col tuo piano reale
A21: Manutenzione, cap massimo (solo Smart) | B21: 100 | D21: Prezzi.jsx — certo (è il tetto dichiarato)
A22: % di utilizzo reale del cap manutenzione | B22: 0.5 | D22: STIMA — nessun dato storico ancora, aggiorna dopo i primi mesi reali
A24: Struttura legale assunta
A25: Mandato SENZA rappresentanza (tu incassi, poi giri il netto al proprietario)
A26: Da confermare con il commercialista — cambia obblighi di ritenuta d'acconto. Vedi nota nel contratto.
A28: Reddito minimo mensile desiderato (per il breakeven)
A29: Il tuo obiettivo di reddito netto mensile dal business | B29: 2000 | D29: SOSTITUISCI col numero vero — decide quante proprietà ti servono davvero

Sheet Costi Fissi Azienda
A1: Costi Fissi Mensili — indipendenti dal numero di immobili
A2: Questi costi esistono anche con zero clienti — sono il tuo punto di partenza per il breakeven.
A4: Voce | B4: €/mese | C4: Nota
A5: Vercel (hosting) | B5: 20 | C5: Free tier a basso traffico, poi Pro
A6: Supabase (database + auth) | B6: 25 | C6: Free tier iniziale, poi Pro
A7: Upstash Redis (rate limiting) | B7: 10 | C7: Pay-as-you-go, stima a basso volume
A8: Calendly | B8: 10 | C8: Piano Essentials
A9: Dominio + email professionale | B9: 5 | C9: Costo annuo ammortizzato al mese
A10: PEC | B10: 1 | C10: Costo annuo ammortizzato al mese
A11: Commercialista | B11: 100 | C11: STIMA — verifica col tuo preventivo reale
A12: Assicurazione RC professionale | B12: 40 | C12: STIMA — verifica polizza reale, valutane la necessità
A14: TOTALE COSTI FISSI MENSILI | B14: =SUM(B5:B13) -> 211

Sheet P&L per Tier
A1: P&L per Tier — 3 Esempi (stesso motore di stima del form)
A3: Esempio 1 — Monolocale, Bicocca
B4: Essenziale | C4: Smart | D4: Premium
A5: Revenue lordo (owner) | B5: 850 | C5: 850 | D5: 850
A6: Commissione / fee VirtualBNB | B6: =B5*Assunzioni!$B$6 -> 212.5 | C6: =C5*Assunzioni!$B$7 -> 238 | D6: =Assunzioni!$B$8 -> 650
A7: Net owner (dopo commissione) | B7: =B5-B6 -> 637.5 | C7: =C5-C6 -> 612 | D7: =D5-D6 -> 200
A8: Costi VirtualBNB — tool (AI + PriceLabs) | B8: =Assunzioni!$B$19+Assunzioni!$B$20 -> 24 | C8: =Assunzioni!$B$19+Assunzioni!$B$20 -> 24 | D8: =Assunzioni!$B$19+Assunzioni!$B$20 -> 24
A9: Costi manutenzione (solo Smart) | B9: 0 | C9: =Assunzioni!$B$21*Assunzioni!$B$22 -> 50 | D9: 0
A10: Margine netto VirtualBNB (esclude il tuo tempo) | B10: =B6-B8-B9 -> 188.5 | C10: =C6-C8-C9 -> 164 | D10: =D6-D8-D9 -> 626
A13: Esempio 2 — Bilocale, Navigli
B14: Essenziale | C14: Smart | D14: Premium
A15: Revenue lordo (owner) | B15: 2120 | C15: 2120 | D15: 2120
A16: Commissione / fee VirtualBNB | B16: =B15*Assunzioni!$B$6 -> 530 | C16: =C15*Assunzioni!$B$7 -> 593.6 | D16: =Assunzioni!$B$8 -> 650
A17: Net owner (dopo commissione) | B17: =B15-B16 -> 1590 | C17: =C15-C16 -> 1526.4 | D17: =D15-D16 -> 1470
A18: Costi VirtualBNB — tool (AI + PriceLabs) | B18: =Assunzioni!$B$19+Assunzioni!$B$20 -> 24 | C18: =Assunzioni!$B$19+Assunzioni!$B$20 -> 24 | D18: =Assunzioni!$B$19+Assunzioni!$B$20 -> 24
A19: Costi manutenzione (solo Smart) | B19: 0 | C19: =Assunzioni!$B$21*Assunzioni!$B$22 -> 50 | D19: 0
A20: Margine netto VirtualBNB (esclude il tuo tempo) | B20: =B16-B18-B19 -> 506 | C20: =C16-C18-C19 -> 519.6 | D20: =D16-D18-D19 -> 626
A23: Esempio 3 — Trilocale, Centro Storico
B24: Essenziale | C24: Smart | D24: Premium
A25: Revenue lordo (owner) | B25: 3510 | C25: 3510 | D25: 3510
A26: Commissione / fee VirtualBNB | B26: =B25*Assunzioni!$B$6 -> 877.5 | C26: =C25*Assunzioni!$B$7 -> 982.8 | D26: =Assunzioni!$B$8 -> 650
A27: Net owner (dopo commissione) | B27: =B25-B26 -> 2632.5 | C27: =C25-C26 -> 2527.2 | D27: =D25-D26 -> 2860
A28: Costi VirtualBNB — tool (AI + PriceLabs) | B28: =Assunzioni!$B$19+Assunzioni!$B$20 -> 24 | C28: =Assunzioni!$B$19+Assunzioni!$B$20 -> 24 | D28: =Assunzioni!$B$19+Assunzioni!$B$20 -> 24
A29: Costi manutenzione (solo Smart) | B29: 0 | C29: =Assunzioni!$B$21*Assunzioni!$B$22 -> 50 | D29: 0
A30: Margine netto VirtualBNB (esclude il tuo tempo) | B30: =B26-B28-B29 -> 853.5 | C30: =C26-C28-C29 -> 908.8 | D30: =D26-D28-D29 -> 626
A33: Nota: Premium calcolato ovunque per coerenza formule, ma su Esempio 1 (revenue troppo basso) non è economicamente sensato per il proprietario — vedi documento Word di dettaglio.

Sheet Breakeven
A1: Breakeven — quanti immobili ti servono
A3: Costi fissi mensili azienda | B3: ='Costi Fissi Azienda'!B14 -> 211
A4: Reddito minimo mensile desiderato | B4: =Assunzioni!B29 -> 2000
A5: Totale da coprire ogni mese | B5: =B3+B4 -> 2211
A7: Margine medio per immobile (riferimento: Smart, Esempio 2 — Navigli) | B7: ='P&L per Tier'!C20 -> 519.6 | C7: Cambia il riferimento se il tuo mix reale di immobili è diverso
A9: NUMERO DI IMMOBILI NECESSARI (arrotondato per eccesso) | B9: =ROUNDUP(B5/B7,0) -> 5

Sheet Proiezione 12 Mesi
A1: Proiezione 12 Mesi — scenario di crescita
A3: Mese | B3: 1 | C3: 2 | D3: 3 | E3: 4 | F3: 5 | G3: 6 | H3: 7 | I3: 8 | J3: 9 | K3: 10 | L3: 11 | M3: 12
A4: Nuovi immobili aggiunti nel mese | B4: 1 | C4: 1 | D4: 1 | E4: 1 | F4: 1 | G4: 1 | H4: 1 | I4: 1 | J4: 1 | K4: 1 | L4: 1 | M4: 1
A5: Immobili totali cumulati | B5: =B4 -> 1 | C5: =B5+C4 -> 2 | D5: =C5+D4 -> 3 | E5: =D5+E4 -> 4 | F5: =E5+F4 -> 5 | G5: =F5+G4 -> 6 | H5: =G5+H4 -> 7 | I5: =H5+I4 -> 8 | J5: =I5+J4 -> 9 | ... M5: =L5+M4 -> 12
A6: Margine stimato (immobili × margine medio/immobile) | B6: =B5*Breakeven!$B$7 -> 519.6 | C6: =C5*Breakeven!$B$7 -> 1039.2 | D6: =D5*Breakeven!$B$7 -> 1558.8 | E6: =E5*Breakeven!$B$7 -> 2078.4 | F6: =F5*Breakeven!$B$7 -> 2598 | G6: =G5*Breakeven!$B$7 -> 3117.6 | H6: =H5*Breakeven!$B$7 -> 3637.2 | I6: =I5*Breakeven!$B$7 -> 4156.8 | ... M6: =M5*Breakeven!$B$7 -> 6235.2
A7: Costi fissi azienda | B7: ='Costi Fissi Azienda'!$B$14 -> 211 | C7: ='Costi Fissi Azienda'!$B$14 -> 211 | D7: ='Costi Fissi Azienda'!$B$14 -> 211 | E7: ='Costi Fissi Azienda'!$B$14 -> 211 | F7: ='Costi Fissi Azienda'!$B$14 -> 211 | G7: ='Costi Fissi Azienda'!$B$14 -> 211 | H7: ='Costi Fissi Azienda'!$B$14 -> 211 | I7: ='Costi Fissi Azienda'!$B$14 -> 211 | ... M7: ='Costi Fissi Azienda'!$B$14 -> 211
A8: Margine netto mensile | B8: =B6-B7 -> 308.6 | C8: =C6-C7 -> 828.2 | D8: =D6-D7 -> 1347.8 | E8: =E6-E7 -> 1867.4 | F8: =F6-F7 -> 2387 | G8: =G6-G7 -> 2906.6 | H8: =H6-H7 -> 3426.2 | I8: =I6-I7 -> 3945.8 | ... M8: =M6-M7 -> 6024.2
A9: Margine cumulato | B9: =B8 -> 308.6 | C9: =B9+C8 -> 1136.8 | D9: =C9+D8 -> 2484.6 | E9: =D9+E8 -> 4352 | F9: =E9+F8 -> 6739 | G9: =F9+G8 -> 9645.6 | H9: =G9+H8 -> 13071.8 | I9: =H9+I8 -> 17017.6 | J9: =I9+J8 -> 21483 | ... M9: =L9+M8 -> 37996.8
A11: Nota: assume 1 immobile nuovo al mese (modifica la riga gialla) e mix Smart-tipico come margine medio. Scenario di partenza, non una previsione garantita.
